<?xml version="1.0" encoding="utf-8"?>
<clothing-items>
 <clothing>
  <id>
   996698347
  </id>
  <name>
   Asics Handbags Q-8806
  </name>
  <category>
   Handbags
  </category>
  <size>
   M
  </size>
  <color>
   Оранжевый
  </color>
  <material>
   Кожа
  </material>
  <price>
   748725
  </price>
  <rating>
   3.56
  </rating>
  <reviews>
   802886
  </reviews>
  <new>
   -
  </new>
  <sporty>
   no
  </sporty>
 </clothing>
 <clothing>
  <id>
   283488118
  </id>
  <name>
   Puma Socks H-1713
  </name>
  <category>
   Socks
  </category>
  <size>
   XL
  </size>
  <color>
   Синий
  </color>
  <material>
   Шерсть
  </material>
  <price>
   940234
  </price>
  <rating>
   2.57
  </rating>
  <reviews>
   365583
  </reviews>
  <new>
   +
  </new>
  <exclusive>
   no
  </exclusive>
 </clothing>
 <clothing>
  <id>
   280983822
  </id>
  <name>
   New Balance Pants X-7069
  </name>
  <category>
   Pants
  </category>
  <size>
   XL
  </size>
  <color>
   Оранжевый
  </color>
  <material>
   Шелк
  </material>
  <price>
   515428
  </price>
  <rating>
   4.01
  </rating>
  <reviews>
   428720
  </reviews>
  <new>
   -
  </new>
  <exclusive>
   no
  </exclusive>
 </clothing>
 <clothing>
  <id>
   677328804
  </id>
  <name>
   Vans Sweater L-6420
  </name>
  <category>
   Sweater
  </category>
  <size>
   XL
  </size>
  <color>
   Оранжевый
  </color>
  <material>
   Шерсть
  </material>
  <price>
   999386
  </price>
  <rating>
   1.56
  </rating>
  <reviews>
   572984
  </reviews>
  <exclusive>
   no
  </exclusive>
  <sporty>
   no
  </sporty>
 </clothing>
 <clothing>
  <id>
   946918117
  </id>
  <name>
   Converse Pants T-8792
  </name>
  <category>
   Pants
  </category>
  <size>
   XL
  </size>
  <color>
   Желтый
  </color>
  <material>
   Шерсть
  </material>
  <price>
   690877
  </price>
  <rating>
   2.15
  </rating>
  <reviews>
   913989
  </reviews>
  <new>
   +
  </new>
  <sporty>
   no
  </sporty>
 </clothing>
 <clothing>
  <id>
   508309481
  </id>
  <name>
   Adidas Belts Z-7786
  </name>
  <category>
   Belts
  </category>
  <size>
   M
  </size>
  <color>
   Голубой
  </color>
  <material>
   Лен
  </material>
  <price>
   806795
  </price>
  <rating>
   2.42
  </rating>
  <reviews>
   395386
  </reviews>
  <exclusive>
   no
  </exclusive>
  <sporty>
   no
  </sporty>
 </clothing>
 <clothing>
  <id>
   149199550
  </id>
  <name>
   Fila Gloves M-3256
  </name>
  <category>
   Gloves
  </category>
  <size>
   XL
  </size>
  <color>
   Красный
  </color>
  <material>
   Шерсть
  </material>
  <price>
   103077
  </price>
  <rating>
   2.33
  </rating>
  <reviews>
   607942
  </reviews>
  <new>
   -
  </new>
  <exclusive>
   yes
  </exclusive>
  <sporty>
   yes
  </sporty>
 </clothing>
 <clothing>
  <id>
   509605731
  </id>
  <name>
   PleinSport Hat N-1261
  </name>
  <category>
   Hat
  </category>
  <size>
   XXL
  </size>
  <color>
   Голубой
  </color>
  <material>
   Лен
  </material>
  <price>
   223670
  </price>
  <rating>
   2.88
  </rating>
  <reviews>
   647320
  </reviews>
  <new>
   +
  </new>
  <exclusive>
   no
  </exclusive>
  <sporty>
   yes
  </sporty>
 </clothing>
 <clothing>
  <id>
   223753979
  </id>
  <name>
   Lacoste Jeans X-7688
  </name>
  <category>
   Jeans
  </category>
  <size>
   L
  </size>
  <color>
   Оранжевый
  </color>
  <material>
   Хлопок
  </material>
  <price>
   884416
  </price>
  <rating>
   2.78
  </rating>
  <reviews>
   475303
  </reviews>
  <exclusive>
   yes
  </exclusive>
  <sporty>
   no
  </sporty>
 </clothing>
 <clothing>
  <id>
   658911497
  </id>
  <name>
   Lacoste Dress E-8636
  </name>
  <category>
   Dress
  </category>
  <size>
   S
  </size>
  <color>
   Голубой
  </color>
  <material>
   Вискоза
  </material>
  <price>
   835069
  </price>
  <rating>
   4.58
  </rating>
  <reviews>
   132764
  </reviews>
  <new>
   +
  </new>
  <exclusive>
   yes
  </exclusive>
 </clothing>
 <clothing>
  <id>
   637662998
  </id>
  <name>
   Adidas Jeans R-3589
  </name>
  <category>
   Jeans
  </category>
  <size>
   L
  </size>
  <color>
   Красный
  </color>
  <material>
   Полиэстер
  </material>
  <price>
   598817
  </price>
  <rating>
   2.28
  </rating>
  <reviews>
   122327
  </reviews>
  <new>
   -
  </new>
  <exclusive>
   yes
  </exclusive>
  <sporty>
   yes
  </sporty>
 </clothing>
 <clothing>
  <id>
   177346094
  </id>
  <name>
   Ellesse Handbags A-2602
  </name>
  <category>
   Handbags
  </category>
  <size>
   S
  </size>
  <color>
   Голубой
  </color>
  <material>
   Шерсть
  </material>
  <price>
   553499
  </price>
  <rating>
   3.26
  </rating>
  <reviews>
   534976
  </reviews>
 </clothing>
</clothing-items>
