<?xml version="1.0" encoding="utf-8"?>
<clothing-items>
 <clothing>
  <id>
   127486170
  </id>
  <name>
   Vans T-shirt I-2733
  </name>
  <category>
   T-shirt
  </category>
  <size>
   M
  </size>
  <color>
   Фиолетовый
  </color>
  <material>
   Шерсть
  </material>
  <price>
   254444
  </price>
  <rating>
   4.59
  </rating>
  <reviews>
   200425
  </reviews>
 </clothing>
 <clothing>
  <id>
   723486163
  </id>
  <name>
   Ellesse Shoes W-5335
  </name>
  <category>
   Shoes
  </category>
  <size>
   XL
  </size>
  <color>
   Красный
  </color>
  <material>
   Нейлон
  </material>
  <price>
   766442
  </price>
  <rating>
   4.24
  </rating>
  <reviews>
   767869
  </reviews>
 </clothing>
 <clothing>
  <id>
   876973939
  </id>
  <name>
   Adidas Skirt Y-2197
  </name>
  <category>
   Skirt
  </category>
  <size>
   XXL
  </size>
  <color>
   Голубой
  </color>
  <material>
   Шерсть
  </material>
  <price>
   150982
  </price>
  <rating>
   3.38
  </rating>
  <reviews>
   143780
  </reviews>
 </clothing>
 <clothing>
  <id>
   156199904
  </id>
  <name>
   Converse Blouse T-5232
  </name>
  <category>
   Blouse
  </category>
  <size>
   S
  </size>
  <color>
   Синий
  </color>
  <material>
   Шелк
  </material>
  <price>
   392917
  </price>
  <rating>
   2.63
  </rating>
  <reviews>
   29149
  </reviews>
  <new>
   -
  </new>
  <exclusive>
   no
  </exclusive>
 </clothing>
 <clothing>
  <id>
   481519263
  </id>
  <name>
   Puma Jeans T-1904
  </name>
  <category>
   Jeans
  </category>
  <size>
   S
  </size>
  <color>
   Оранжевый
  </color>
  <material>
   Полиэстер
  </material>
  <price>
   694660
  </price>
  <rating>
   4.3
  </rating>
  <reviews>
   304016
  </reviews>
  <exclusive>
   no
  </exclusive>
  <sporty>
   no
  </sporty>
 </clothing>
 <clothing>
  <id>
   745137073
  </id>
  <name>
   Reebok Blouse Y-5543
  </name>
  <category>
   Blouse
  </category>
  <size>
   XL
  </size>
  <color>
   Зеленый
  </color>
  <material>
   Шелк
  </material>
  <price>
   671698
  </price>
  <rating>
   2.2
  </rating>
  <reviews>
   274033
  </reviews>
  <new>
   +
  </new>
  <sporty>
   yes
  </sporty>
 </clothing>
 <clothing>
  <id>
   308268018
  </id>
  <name>
   PleinSport Sweater V-5177
  </name>
  <category>
   Sweater
  </category>
  <size>
   XXL
  </size>
  <color>
   Оранжевый
  </color>
  <material>
   Шелк
  </material>
  <price>
   238607
  </price>
  <rating>
   4.22
  </rating>
  <reviews>
   192238
  </reviews>
  <new>
   -
  </new>
  <exclusive>
   yes
  </exclusive>
 </clothing>
 <clothing>
  <id>
   914635421
  </id>
  <name>
   Converse Handbags S-8668
  </name>
  <category>
   Handbags
  </category>
  <size>
   S
  </size>
  <color>
   Оранжевый
  </color>
  <material>
   Полиэстер
  </material>
  <price>
   957432
  </price>
  <rating>
   3.34
  </rating>
  <reviews>
   545748
  </reviews>
  <new>
   +
  </new>
  <exclusive>
   yes
  </exclusive>
  <sporty>
   no
  </sporty>
 </clothing>
 <clothing>
  <id>
   383940792
  </id>
  <name>
   Vans Pants J-5690
  </name>
  <category>
   Pants
  </category>
  <size>
   XL
  </size>
  <color>
   Фиолетовый
  </color>
  <material>
   Нейлон
  </material>
  <price>
   948384
  </price>
  <rating>
   2.91
  </rating>
  <reviews>
   656474
  </reviews>
 </clothing>
 <clothing>
  <id>
   321599134
  </id>
  <name>
   Adidas Dress W-9276
  </name>
  <category>
   Dress
  </category>
  <size>
   L
  </size>
  <color>
   Оранжевый
  </color>
  <material>
   Хлопок
  </material>
  <price>
   865399
  </price>
  <rating>
   1.54
  </rating>
  <reviews>
   503995
  </reviews>
  <new>
   +
  </new>
  <exclusive>
   no
  </exclusive>
  <sporty>
   no
  </sporty>
 </clothing>
 <clothing>
  <id>
   142330997
  </id>
  <name>
   Ellesse Jacket J-4801
  </name>
  <category>
   Jacket
  </category>
  <size>
   L
  </size>
  <color>
   Фиолетовый
  </color>
  <material>
   Лен
  </material>
  <price>
   610965
  </price>
  <rating>
   3.57
  </rating>
  <reviews>
   225951
  </reviews>
  <new>
   -
  </new>
  <exclusive>
   yes
  </exclusive>
  <sporty>
   no
  </sporty>
 </clothing>
 <clothing>
  <id>
   995574078
  </id>
  <name>
   Lacoste Shoes M-8291
  </name>
  <category>
   Shoes
  </category>
  <size>
   L
  </size>
  <color>
   Красный
  </color>
  <material>
   Вискоза
  </material>
  <price>
   327031
  </price>
  <rating>
   4.99
  </rating>
  <reviews>
   227290
  </reviews>
  <new>
   +
  </new>
 </clothing>
 <clothing>
  <id>
   150684890
  </id>
  <name>
   PleinSport Pants N-5754
  </name>
  <category>
   Pants
  </category>
  <size>
   L
  </size>
  <color>
   Желтый
  </color>
  <material>
   Вискоза
  </material>
  <price>
   771559
  </price>
  <rating>
   3.42
  </rating>
  <reviews>
   843095
  </reviews>
  <exclusive>
   no
  </exclusive>
  <sporty>
   yes
  </sporty>
 </clothing>
 <clothing>
  <id>
   786128981
  </id>
  <name>
   Brooks Socks J-9853
  </name>
  <category>
   Socks
  </category>
  <size>
   M
  </size>
  <color>
   Зеленый
  </color>
  <material>
   Шелк
  </material>
  <price>
   715217
  </price>
  <rating>
   1.58
  </rating>
  <reviews>
   142464
  </reviews>
  <new>
   -
  </new>
  <exclusive>
   yes
  </exclusive>
  <sporty>
   yes
  </sporty>
 </clothing>
 <clothing>
  <id>
   866074407
  </id>
  <name>
   Vans Handbags U-7707
  </name>
  <category>
   Handbags
  </category>
  <size>
   XXL
  </size>
  <color>
   Голубой
  </color>
  <material>
   Вискоза
  </material>
  <price>
   973562
  </price>
  <rating>
   1.28
  </rating>
  <reviews>
   911897
  </reviews>
  <new>
   +
  </new>
  <exclusive>
   yes
  </exclusive>
  <sporty>
   no
  </sporty>
 </clothing>
 <clothing>
  <id>
   430541787
  </id>
  <name>
   Nike Pants Y-5168
  </name>
  <category>
   Pants
  </category>
  <size>
   XXL
  </size>
  <color>
   Зеленый
  </color>
  <material>
   Нейлон
  </material>
  <price>
   869302
  </price>
  <rating>
   3.3
  </rating>
  <reviews>
   582642
  </reviews>
  <exclusive>
   no
  </exclusive>
  <sporty>
   yes
  </sporty>
 </clothing>
 <clothing>
  <id>
   859982231
  </id>
  <name>
   Fila Jacket S-9502
  </name>
  <category>
   Jacket
  </category>
  <size>
   XXL
  </size>
  <color>
   Желтый
  </color>
  <material>
   Хлопок
  </material>
  <price>
   606384
  </price>
  <rating>
   4.44
  </rating>
  <reviews>
   878477
  </reviews>
  <new>
   +
  </new>
  <exclusive>
   no
  </exclusive>
 </clothing>
 <clothing>
  <id>
   248550528
  </id>
  <name>
   New Balance Pants Q-3413
  </name>
  <category>
   Pants
  </category>
  <size>
   M
  </size>
  <color>
   Синий
  </color>
  <material>
   Кожа
  </material>
  <price>
   880314
  </price>
  <rating>
   2.81
  </rating>
  <reviews>
   612389
  </reviews>
  <exclusive>
   no
  </exclusive>
  <sporty>
   no
  </sporty>
 </clothing>
 <clothing>
  <id>
   350585162
  </id>
  <name>
   Puma Umbrellas K-7335
  </name>
  <category>
   Umbrellas
  </category>
  <size>
   S
  </size>
  <color>
   Фиолетовый
  </color>
  <material>
   Вискоза
  </material>
  <price>
   173878
  </price>
  <rating>
   2.93
  </rating>
  <reviews>
   890976
  </reviews>
  <new>
   +
  </new>
  <exclusive>
   no
  </exclusive>
 </clothing>
 <clothing>
  <id>
   266658368
  </id>
  <name>
   Adidas Socks I-6917
  </name>
  <category>
   Socks
  </category>
  <size>
   S
  </size>
  <color>
   Оранжевый
  </color>
  <material>
   Шерсть
  </material>
  <price>
   852675
  </price>
  <rating>
   5.0
  </rating>
  <reviews>
   886121
  </reviews>
  <new>
   +
  </new>
 </clothing>
 <clothing>
  <id>
   834186333
  </id>
  <name>
   Reebok Handbags Q-1974
  </name>
  <category>
   Handbags
  </category>
  <size>
   L
  </size>
  <color>
   Желтый
  </color>
  <material>
   Нейлон
  </material>
  <price>
   768833
  </price>
  <rating>
   4.93
  </rating>
  <reviews>
   661365
  </reviews>
  <new>
   -
  </new>
  <exclusive>
   yes
  </exclusive>
 </clothing>
 <clothing>
  <id>
   209287117
  </id>
  <name>
   Asics Umbrellas T-4267
  </name>
  <category>
   Umbrellas
  </category>
  <size>
   M
  </size>
  <color>
   Фиолетовый
  </color>
  <material>
   Хлопок
  </material>
  <price>
   619915
  </price>
  <rating>
   1.8
  </rating>
  <reviews>
   999722
  </reviews>
  <new>
   -
  </new>
  <exclusive>
   yes
  </exclusive>
 </clothing>
 <clothing>
  <id>
   214553971
  </id>
  <name>
   Puma Shoes T-2081
  </name>
  <category>
   Shoes
  </category>
  <size>
   L
  </size>
  <color>
   Оранжевый
  </color>
  <material>
   Лен
  </material>
  <price>
   644628
  </price>
  <rating>
   4.01
  </rating>
  <reviews>
   277811
  </reviews>
  <exclusive>
   no
  </exclusive>
  <sporty>
   no
  </sporty>
 </clothing>
 <clothing>
  <id>
   795770609
  </id>
  <name>
   Reebok Dress G-9928
  </name>
  <category>
   Dress
  </category>
  <size>
   S
  </size>
  <color>
   Синий
  </color>
  <material>
   Лен
  </material>
  <price>
   736980
  </price>
  <rating>
   2.08
  </rating>
  <reviews>
   897870
  </reviews>
  <exclusive>
   yes
  </exclusive>
  <sporty>
   yes
  </sporty>
 </clothing>
 <clothing>
  <id>
   346522130
  </id>
  <name>
   Adidas T-shirt F-3201
  </name>
  <category>
   T-shirt
  </category>
  <size>
   L
  </size>
  <color>
   Зеленый
  </color>
  <material>
   Кожа
  </material>
  <price>
   635475
  </price>
  <rating>
   4.84
  </rating>
  <reviews>
   75224
  </reviews>
  <exclusive>
   no
  </exclusive>
  <sporty>
   yes
  </sporty>
 </clothing>
 <clothing>
  <id>
   239912355
  </id>
  <name>
   PleinSport Dress J-8056
  </name>
  <category>
   Dress
  </category>
  <size>
   XL
  </size>
  <color>
   Желтый
  </color>
  <material>
   Полиэстер
  </material>
  <price>
   641808
  </price>
  <rating>
   3.84
  </rating>
  <reviews>
   537185
  </reviews>
  <new>
   +
  </new>
  <exclusive>
   yes
  </exclusive>
 </clothing>
 <clothing>
  <id>
   560212201
  </id>
  <name>
   Under Armour Skirt B-8429
  </name>
  <category>
   Skirt
  </category>
  <size>
   XL
  </size>
  <color>
   Красный
  </color>
  <material>
   Нейлон
  </material>
  <price>
   295141
  </price>
  <rating>
   1.75
  </rating>
  <reviews>
   33116
  </reviews>
  <new>
   -
  </new>
  <sporty>
   no
  </sporty>
 </clothing>
 <clothing>
  <id>
   954957131
  </id>
  <name>
   Nike Gloves E-9025
  </name>
  <category>
   Gloves
  </category>
  <size>
   S
  </size>
  <color>
   Желтый
  </color>
  <material>
   Кожа
  </material>
  <price>
   846729
  </price>
  <rating>
   4.96
  </rating>
  <reviews>
   533936
  </reviews>
  <exclusive>
   no
  </exclusive>
  <sporty>
   no
  </sporty>
 </clothing>
 <clothing>
  <id>
   869253157
  </id>
  <name>
   Under Armour Jacket Z-5718
  </name>
  <category>
   Jacket
  </category>
  <size>
   M
  </size>
  <color>
   Зеленый
  </color>
  <material>
   Кожа
  </material>
  <price>
   873774
  </price>
  <rating>
   4.68
  </rating>
  <reviews>
   608787
  </reviews>
  <new>
   -
  </new>
  <exclusive>
   yes
  </exclusive>
  <sporty>
   yes
  </sporty>
 </clothing>
 <clothing>
  <id>
   316381817
  </id>
  <name>
   Lacoste Belts M-5545
  </name>
  <category>
   Belts
  </category>
  <size>
   L
  </size>
  <color>
   Голубой
  </color>
  <material>
   Шелк
  </material>
  <price>
   197245
  </price>
  <rating>
   3.19
  </rating>
  <reviews>
   386973
  </reviews>
  <new>
   +
  </new>
  <exclusive>
   yes
  </exclusive>
  <sporty>
   yes
  </sporty>
 </clothing>
 <clothing>
  <id>
   577188117
  </id>
  <name>
   Puma Hat I-1117
  </name>
  <category>
   Hat
  </category>
  <size>
   L
  </size>
  <color>
   Оранжевый
  </color>
  <material>
   Хлопок
  </material>
  <price>
   615732
  </price>
  <rating>
   3.8
  </rating>
  <reviews>
   957480
  </reviews>
  <exclusive>
   no
  </exclusive>
  <sporty>
   no
  </sporty>
 </clothing>
 <clothing>
  <id>
   384520244
  </id>
  <name>
   PleinSport Sweater C-5809
  </name>
  <category>
   Sweater
  </category>
  <size>
   M
  </size>
  <color>
   Синий
  </color>
  <material>
   Хлопок
  </material>
  <price>
   449215
  </price>
  <rating>
   3.63
  </rating>
  <reviews>
   200427
  </reviews>
  <new>
   -
  </new>
  <exclusive>
   no
  </exclusive>
  <sporty>
   yes
  </sporty>
 </clothing>
 <clothing>
  <id>
   259423746
  </id>
  <name>
   Under Armour Umbrellas Y-6794
  </name>
  <category>
   Umbrellas
  </category>
  <size>
   M
  </size>
  <color>
   Красный
  </color>
  <material>
   Шерсть
  </material>
  <price>
   570704
  </price>
  <rating>
   4.35
  </rating>
  <reviews>
   309565
  </reviews>
  <exclusive>
   no
  </exclusive>
 </clothing>
 <clothing>
  <id>
   780949233
  </id>
  <name>
   Nike Handbags S-3881
  </name>
  <category>
   Handbags
  </category>
  <size>
   L
  </size>
  <color>
   Зеленый
  </color>
  <material>
   Полиэстер
  </material>
  <price>
   180765
  </price>
  <rating>
   4.53
  </rating>
  <reviews>
   117716
  </reviews>
 </clothing>
 <clothing>
  <id>
   524991496
  </id>
  <name>
   Nike Jeans E-4593
  </name>
  <category>
   Jeans
  </category>
  <size>
   XL
  </size>
  <color>
   Желтый
  </color>
  <material>
   Нейлон
  </material>
  <price>
   162512
  </price>
  <rating>
   1.94
  </rating>
  <reviews>
   936563
  </reviews>
  <exclusive>
   no
  </exclusive>
  <sporty>
   no
  </sporty>
 </clothing>
 <clothing>
  <id>
   660364094
  </id>
  <name>
   Puma Jacket R-2389
  </name>
  <category>
   Jacket
  </category>
  <size>
   XXL
  </size>
  <color>
   Желтый
  </color>
  <material>
   Вискоза
  </material>
  <price>
   201383
  </price>
  <rating>
   1.19
  </rating>
  <reviews>
   479325
  </reviews>
  <new>
   +
  </new>
 </clothing>
 <clothing>
  <id>
   167858442
  </id>
  <name>
   Addidas Dress W-3550
  </name>
  <category>
   Dress
  </category>
  <size>
   L
  </size>
  <color>
   Зеленый
  </color>
  <material>
   Хлопок
  </material>
  <price>
   758187
  </price>
  <rating>
   1.75
  </rating>
  <reviews>
   16254
  </reviews>
  <exclusive>
   no
  </exclusive>
  <sporty>
   yes
  </sporty>
 </clothing>
 <clothing>
  <id>
   901617976
  </id>
  <name>
   Fila Belts I-5517
  </name>
  <category>
   Belts
  </category>
  <size>
   XXL
  </size>
  <color>
   Оранжевый
  </color>
  <material>
   Кожа
  </material>
  <price>
   780558
  </price>
  <rating>
   3.88
  </rating>
  <reviews>
   516230
  </reviews>
  <new>
   -
  </new>
  <sporty>
   yes
  </sporty>
 </clothing>
 <clothing>
  <id>
   390554067
  </id>
  <name>
   DC Jacket A-6654
  </name>
  <category>
   Jacket
  </category>
  <size>
   XXL
  </size>
  <color>
   Оранжевый
  </color>
  <material>
   Шерсть
  </material>
  <price>
   251591
  </price>
  <rating>
   4.73
  </rating>
  <reviews>
   662599
  </reviews>
  <exclusive>
   no
  </exclusive>
  <sporty>
   no
  </sporty>
 </clothing>
 <clothing>
  <id>
   927075882
  </id>
  <name>
   Asics Sweater K-4815
  </name>
  <category>
   Sweater
  </category>
  <size>
   L
  </size>
  <color>
   Красный
  </color>
  <material>
   Шерсть
  </material>
  <price>
   681473
  </price>
  <rating>
   4.81
  </rating>
  <reviews>
   356766
  </reviews>
  <new>
   -
  </new>
  <exclusive>
   yes
  </exclusive>
  <sporty>
   no
  </sporty>
 </clothing>
 <clothing>
  <id>
   109646591
  </id>
  <name>
   Reebok Hat I-2532
  </name>
  <category>
   Hat
  </category>
  <size>
   L
  </size>
  <color>
   Оранжевый
  </color>
  <material>
   Шерсть
  </material>
  <price>
   811228
  </price>
  <rating>
   4.79
  </rating>
  <reviews>
   187807
  </reviews>
  <new>
   +
  </new>
  <exclusive>
   yes
  </exclusive>
 </clothing>
 <clothing>
  <id>
   219146987
  </id>
  <name>
   Nike Jeans L-9503
  </name>
  <category>
   Jeans
  </category>
  <size>
   S
  </size>
  <color>
   Зеленый
  </color>
  <material>
   Нейлон
  </material>
  <price>
   869130
  </price>
  <rating>
   1.83
  </rating>
  <reviews>
   892369
  </reviews>
  <new>
   +
  </new>
 </clothing>
 <clothing>
  <id>
   518896953
  </id>
  <name>
   PleinSport Shoes O-5418
  </name>
  <category>
   Shoes
  </category>
  <size>
   XL
  </size>
  <color>
   Фиолетовый
  </color>
  <material>
   Лен
  </material>
  <price>
   434290
  </price>
  <rating>
   3.07
  </rating>
  <reviews>
   430620
  </reviews>
  <exclusive>
   no
  </exclusive>
 </clothing>
 <clothing>
  <id>
   240364021
  </id>
  <name>
   Vans Umbrellas K-5752
  </name>
  <category>
   Umbrellas
  </category>
  <size>
   S
  </size>
  <color>
   Голубой
  </color>
  <material>
   Кожа
  </material>
  <price>
   659732
  </price>
  <rating>
   4.83
  </rating>
  <reviews>
   637725
  </reviews>
  <new>
   +
  </new>
  <exclusive>
   yes
  </exclusive>
 </clothing>
 <clothing>
  <id>
   826499482
  </id>
  <name>
   Puma Umbrellas L-6797
  </name>
  <category>
   Umbrellas
  </category>
  <size>
   S
  </size>
  <color>
   Синий
  </color>
  <material>
   Вискоза
  </material>
  <price>
   544909
  </price>
  <rating>
   1.07
  </rating>
  <reviews>
   112887
  </reviews>
  <exclusive>
   yes
  </exclusive>
  <sporty>
   no
  </sporty>
 </clothing>
 <clothing>
  <id>
   384771904
  </id>
  <name>
   PleinSport Hat V-8207
  </name>
  <category>
   Hat
  </category>
  <size>
   XL
  </size>
  <color>
   Зеленый
  </color>
  <material>
   Лен
  </material>
  <price>
   135057
  </price>
  <rating>
   1.93
  </rating>
  <reviews>
   127207
  </reviews>
  <new>
   -
  </new>
  <sporty>
   no
  </sporty>
 </clothing>
 <clothing>
  <id>
   565224528
  </id>
  <name>
   PleinSport Jeans U-5965
  </name>
  <category>
   Jeans
  </category>
  <size>
   L
  </size>
  <color>
   Красный
  </color>
  <material>
   Полиэстер
  </material>
  <price>
   474010
  </price>
  <rating>
   2.91
  </rating>
  <reviews>
   489802
  </reviews>
  <new>
   +
  </new>
  <exclusive>
   no
  </exclusive>
 </clothing>
</clothing-items>
